odoo9_addon_crm_claim_type-9.0.1.0.0.99.dev38-py3.8-nspkg.pth
odoo_addons/crm_claim_type/README.rst
odoo_addons/crm_claim_type/__init__.py
odoo_addons/crm_claim_type/__openerp__.py
odoo_addons/crm_claim_type/data/crm_claim_stage.xml
odoo_addons/crm_claim_type/data/crm_claim_type.xml
odoo_addons/crm_claim_type/demo/crm_claim.xml
odoo_addons/crm_claim_type/demo/crm_claim_stage.xml
odoo_addons/crm_claim_type/i18n/am.po
odoo_addons/crm_claim_type/i18n/ar.po
odoo_addons/crm_claim_type/i18n/bg.po
odoo_addons/crm_claim_type/i18n/bs.po
odoo_addons/crm_claim_type/i18n/ca.po
odoo_addons/crm_claim_type/i18n/ca_ES.po
odoo_addons/crm_claim_type/i18n/crm_claim_type.pot
odoo_addons/crm_claim_type/i18n/cs.po
odoo_addons/crm_claim_type/i18n/da.po
odoo_addons/crm_claim_type/i18n/de.po
odoo_addons/crm_claim_type/i18n/el_GR.po
odoo_addons/crm_claim_type/i18n/en_GB.po
odoo_addons/crm_claim_type/i18n/es.po
odoo_addons/crm_claim_type/i18n/es_AR.po
odoo_addons/crm_claim_type/i18n/es_CL.po
odoo_addons/crm_claim_type/i18n/es_CO.po
odoo_addons/crm_claim_type/i18n/es_CR.po
odoo_addons/crm_claim_type/i18n/es_DO.po
odoo_addons/crm_claim_type/i18n/es_EC.po
odoo_addons/crm_claim_type/i18n/es_ES.po
odoo_addons/crm_claim_type/i18n/es_MX.po
odoo_addons/crm_claim_type/i18n/es_PA.po
odoo_addons/crm_claim_type/i18n/es_PE.po
odoo_addons/crm_claim_type/i18n/es_PY.po
odoo_addons/crm_claim_type/i18n/es_VE.po
odoo_addons/crm_claim_type/i18n/et.po
odoo_addons/crm_claim_type/i18n/eu.po
odoo_addons/crm_claim_type/i18n/eu_ES.po
odoo_addons/crm_claim_type/i18n/fa.po
odoo_addons/crm_claim_type/i18n/fi.po
odoo_addons/crm_claim_type/i18n/fr.po
odoo_addons/crm_claim_type/i18n/fr_CA.po
odoo_addons/crm_claim_type/i18n/fr_CH.po
odoo_addons/crm_claim_type/i18n/fr_FR.po
odoo_addons/crm_claim_type/i18n/gl.po
odoo_addons/crm_claim_type/i18n/gl_ES.po
odoo_addons/crm_claim_type/i18n/he.po
odoo_addons/crm_claim_type/i18n/hr.po
odoo_addons/crm_claim_type/i18n/hr_HR.po
odoo_addons/crm_claim_type/i18n/hu.po
odoo9_addon_crm_claim_type-9.0.1.0.0.99.dev38.dist-info/METADATA
odoo9_addon_crm_claim_type-9.0.1.0.0.99.dev38.dist-info/WHEEL
odoo9_addon_crm_claim_type-9.0.1.0.0.99.dev38.dist-info/namespace_packages.txt
odoo9_addon_crm_claim_type-9.0.1.0.0.99.dev38.dist-info/top_level.txt
odoo9_addon_crm_claim_type-9.0.1.0.0.99.dev38.dist-info/RECORD
