Metadata-Version: 2.1
Name: odoo9-addon-crm-claim-type
Version: 9.0.1.0.0.99.dev38
Summary: Claim types for CRM
Home-page: https://www.vauxoo.com/
Author: Odoo Community Association (OCA),Vauxoo
Author-email: support@odoo-community.org
License: AGPL-3
Platform: UNKNOWN
Classifier: Programming Language :: Python
Classifier: Framework :: Odoo
Classifier: Framework :: Odoo :: 9.0
Classifier: License :: OSI Approved :: GNU Affero General Public License v3
Requires-Python: ~=2.7
Requires-Dist: odoo (<9.1a,>=9.0a)
